AD_Derivators/__init__.py
AD_Derivators/rootfinder.py
AD_Derivators/functions/__init__.py
AD_Derivators/functions/autograd.py
AD_Derivators/functions/tensor.py
AD_Derivators/helper_functions/__init__.py
AD_Derivators/helper_functions/ad_utils.py
tests/__init__.py
tests/test_autograd.py
tests/test_rootfinder.py
tests/test_tensor.py
AD_Derivators-0.0.2.dist-info/LICENSE
AD_Derivators-0.0.2.dist-info/METADATA
AD_Derivators-0.0.2.dist-info/WHEEL
AD_Derivators-0.0.2.dist-info/top_level.txt
AD_Derivators-0.0.2.dist-info/RECORD
