Metadata-Version: 2.1
Name: AD-Derivators
Version: 0.0.2
Summary: Auto-Differentiation Package based on Forward Mode
Home-page: https://github.com/DERIVATORS
Author: Alice Li, Ethan Schumann, Ruizhe Kang, Vikram Shastry
Author-email: anqili@g.harvard.edu
License: UNKNOWN
Platform: UNKNOWN
Classifier: Programming Language :: Python :: 3
Classifier: License :: OSI Approved :: MIT License
Classifier: Operating System :: OS Independent
Requires-Python: >=3.6
